yonata/__init__.py
yonata/__main__.py
yonata/printers.py
yonata-0.1.3.dist-info/METADATA
yonata-0.1.3.dist-info/WHEEL
yonata-0.1.3.dist-info/RECORD
