Metadata-Version: 2.3
Name: yonata
Version: 0.1.3
Summary: 
Author: Erwin Yonata
Author-email: erwinwingyonata@gmail.com
Requires-Python: >=3.10
Classifier: Programming Language :: Python :: 3
Classifier: Programming Language :: Python :: 3.10
Classifier: Programming Language :: Python :: 3.11
Classifier: Programming Language :: Python :: 3.12
Classifier: Programming Language :: Python :: 3.13
Requires-Dist: numpy (>=1.25.2,<3.0.0)
Requires-Dist: requests (>=2.32.3,<3.0.0)
